{
    "paperId": "24cd6c96ab96416299f30d078d114276aa2fccae",
    "externalIds": {
        "DBLP": "journals/corr/abs-2407-18002",
        "ArXiv": "2407.18002",
        "DOI": "10.48550/arXiv.2407.18002",
        "CorpusId": 271431942
    },
    "title": "Network Inversion of Convolutional Neural Nets",
    "abstract": "Neural networks have emerged as powerful tools across various applications, yet their decision-making process often remains opaque, leading to them being perceived as\"black boxes.\"This opacity raises concerns about their interpretability and reliability, especially in safety-critical scenarios. Network inversion techniques offer a solution by allowing us to peek inside these black boxes, revealing the features and patterns learned by the networks behind their decision-making processes and thereby provide valuable insights into how neural networks arrive at their conclusions, making them more interpretable and trustworthy. This paper presents a simple yet effective approach to network inversion using a carefully conditioned generator that learns the data distribution in the input space of the trained neural network, enabling the reconstruction of inputs that would most likely lead to the desired outputs. To capture the diversity in the input space for a given output, instead of simply revealing the conditioning labels to the generator, we hideously encode the conditioning label information into vectors, further exemplified by heavy dropout in the generation process and minimisation of cosine similarity between the features corresponding to the generated images. The paper concludes with immediate applications of Network Inversion including in interpretability, explainability and generation of adversarial samples.",
    "venue": "arXiv.org",
    "year": 2024,
    "referenceCount": 7,
    "citationCount": 0,
    "influentialCitationCount": 0,
    "openAccessPdf": null,
    "tldr": {
        "model": "tldr@v2.0.0",
        "text": "This paper presents a simple yet effective approach to network inversion using a carefully conditioned generator that learns the data distribution in the input space of the trained neural network, enabling the reconstruction of inputs that would most likely lead to the desired outputs."
    },
    "embedding": {
        "model": "specter_v1",
        "vector": [
            2.3533151149749756,
            -0.886432409286499,
            1.7058916091918945,
            4.173289775848389,
            0.9696020483970642,
            -2.6082441806793213,
            1.939619541168213,
            -1.861901044845581,
            -1.0482256412506104,
            1.3129814863204956,
            -4.759243011474609,
            4.004486083984375,
            0.5302378535270691,
            -0.09235596656799316,
            -4.297117233276367,
            0.738548755645752,
            -1.8219938278198242,
            2.8511455059051514,
            2.7387073040008545,
            2.8249945640563965,
            -0.8107383847236633,
            -0.3785887360572815,
            -0.31039273738861084,
            0.49361246824264526,
            -3.6981701850891113,
            -0.765404999256134,
            2.1834726333618164,
            -0.8089369535446167,
            -2.161982297897339,
            1.9507639408111572,
            1.302032470703125,
            -3.3691625595092773,
            5.308354377746582,
            -1.9548625946044922,
            3.0351595878601074,
            0.05372416973114014,
            -0.16129201650619507,
            6.321783065795898,
            -4.094883441925049,
            -0.5397088527679443,
            -0.8470975160598755,
            0.05656634271144867,
            4.471922397613525,
            0.43904465436935425,
            0.18531331419944763,
            1.0263845920562744,
            -0.38044193387031555,
            0.2881823480129242,
            -0.699212372303009,
            3.778679370880127,
            1.0529063940048218,
            0.0779215395450592,
            -0.669671893119812,
            -1.3831814527511597,
            -2.100813388824463,
            -2.0091772079467773,
            -0.03273165225982666,
            -0.7745263576507568,
            -0.7490797638893127,
            -2.605431079864502,
            2.5018837451934814,
            3.8244595527648926,
            -0.05455571413040161,
            -3.6730990409851074,
            4.682810306549072,
            -3.9578588008880615,
            -0.13429230451583862,
            3.216890335083008,
            2.9279327392578125,
            -0.9399660229682922,
            -4.128450393676758,
            -2.4451534748077393,
            1.636955976486206,
            0.2610679864883423,
            -1.9293534755706787,
            0.6375961303710938,
            -1.0167415142059326,
            -1.6880509853363037,
            -0.34176939725875854,
            -0.740925133228302,
            1.700605869293213,
            2.359431743621826,
            -1.9852964878082275,
            4.7031378746032715,
            0.9418804049491882,
            1.2335948944091797,
            -0.9568148255348206,
            -4.570782661437988,
            0.7261807918548584,
            -2.7066187858581543,
            0.05485031008720398,
            -0.3943302631378174,
            1.6866888999938965,
            -1.5371226072311401,
            -5.16713285446167,
            0.3716999888420105,
            2.160397529602051,
            -1.893292784690857,
            -2.1945786476135254,
            1.631841778755188,
            2.5296072959899902,
            -1.932424783706665,
            3.4487502574920654,
            -0.8756557703018188,
            7.004759311676025,
            -3.5760562419891357,
            1.1710922718048096,
            1.532804250717163,
            1.546077847480774,
            -3.593766689300537,
            -1.936720609664917,
            0.1125006377696991,
            -2.738145589828491,
            3.965104579925537,
            -0.7342987060546875,
            4.135322093963623,
            -0.1420261263847351,
            -0.13431723415851593,
            -2.920161008834839,
            2.5539700984954834,
            -1.68654203414917,
            -4.520566940307617,
            -3.6580817699432373,
            2.4429233074188232,
            -2.983654022216797,
            -1.3615758419036865,
            0.8207274675369263,
            4.418498516082764,
            0.540955662727356,
            -2.196944236755371,
            6.275826930999756,
            -3.056547164916992,
            -0.1711498200893402,
            0.6405304670333862,
            -0.41034600138664246,
            3.1931512355804443,
            -0.8312658667564392,
            2.783470392227173,
            -1.874671220779419,
            0.5511777400970459,
            1.5236003398895264,
            2.090564489364624,
            1.082843542098999,
            0.2018442004919052,
            -0.6623785495758057,
            4.871160507202148,
            0.24010933935642242,
            4.945593357086182,
            0.8478974103927612,
            4.0026960372924805,
            3.9708311557769775,
            -2.4757027626037598,
            1.8099968433380127,
            2.917365074157715,
            2.817793369293213,
            6.57212495803833,
            -6.933959007263184,
            1.2177610397338867,
            -0.37704187631607056,
            0.365667462348938,
            -1.0753488540649414,
            -2.2290093898773193,
            -11.894742965698242,
            -1.9726767539978027,
            1.6826984882354736,
            -5.006442546844482,
            -1.686156153678894,
            2.4186668395996094,
            -1.6792972087860107,
            1.5956659317016602,
            1.348574161529541,
            4.019901275634766,
            2.8700923919677734,
            4.965573310852051,
            2.538973808288574,
            4.882513523101807,
            0.02823139727115631,
            -3.502626419067383,
            -0.9653414487838745,
            -0.8005688190460205,
            -0.48506873846054077,
            0.06214141845703125,
            -4.941361427307129,
            1.11052668094635,
            -2.7314109802246094,
            -6.482054710388184,
            -2.1262452602386475,
            0.004695892333984375,
            -3.5807952880859375,
            -0.21654295921325684,
            1.546318531036377,
            1.7418910264968872,
            3.3189239501953125,
            5.515875816345215,
            0.14343708753585815,
            1.3161017894744873,
            3.338454246520996,
            1.720097303390503,
            -2.0357351303100586,
            2.521439552307129,
            2.945336103439331,
            -0.14459282159805298,
            -2.589658737182617,
            0.48417964577674866,
            2.327956199645996,
            2.1952691078186035,
            -4.458709716796875,
            2.8222858905792236,
            2.0445194244384766,
            -0.44288575649261475,
            0.36921605467796326,
            0.43142569065093994,
            -0.6423684358596802,
            6.464935302734375,
            -4.387836933135986,
            1.124275803565979,
            -4.587828159332275,
            4.760228633880615,
            5.089799880981445,
            3.132701873779297,
            -2.262127161026001,
            -0.10168388485908508,
            -1.9702147245407104,
            -0.9465086460113525,
            -0.018341034650802612,
            -5.094621658325195,
            2.54943585395813,
            -0.3479762673377991,
            2.1958327293395996,
            1.6913738250732422,
            -0.6902163028717041,
            -5.429880619049072,
            0.6228491067886353,
            0.35686761140823364,
            -6.756283760070801,
            0.5638304948806763,
            -5.1675825119018555,
            1.3243834972381592,
            0.997904360294342,
            -0.680814802646637,
            4.892817974090576,
            -0.3696210980415344,
            -0.9738078117370605,
            0.6726914644241333,
            3.671804189682007,
            -1.4270278215408325,
            -6.302049160003662,
            2.755542039871216,
            2.6984169483184814,
            -1.05281662940979,
            -3.2165915966033936,
            -1.0978777408599854,
            1.9215540885925293,
            -3.299213409423828,
            2.080568790435791,
            0.10821934044361115,
            3.6455414295196533,
            1.8327815532684326,
            0.15616357326507568,
            -2.0173518657684326,
            0.15663635730743408,
            1.7652029991149902,
            -1.378813624382019,
            -0.5251847505569458,
            -3.365105152130127,
            -2.4051196575164795,
            -0.5818401575088501,
            -1.186112642288208,
            -1.2397925853729248,
            1.9110108613967896,
            0.6566410064697266,
            -3.4437928199768066,
            -0.6692560911178589,
            -1.1991463899612427,
            -0.8348681330680847,
            -3.2144007682800293,
            -2.4590792655944824,
            -1.8459606170654297,
            2.0589470863342285,
            3.3291585445404053,
            2.0629723072052,
            -4.635246276855469,
            -0.19889941811561584,
            -0.6510263085365295,
            -0.885367751121521,
            -5.360394477844238,
            -1.3113082647323608,
            0.590143084526062,
            1.667325496673584,
            -1.5539495944976807,
            -3.018249034881592,
            2.449220895767212,
            -5.299635887145996,
            -0.7670894861221313,
            -2.362997531890869,
            2.116497278213501,
            2.5994246006011963,
            -0.6306769847869873,
            0.03359043598175049,
            3.199775457382202,
            -1.9023888111114502,
            1.3532686233520508,
            4.636081218719482,
            -4.513157367706299,
            0.6921734809875488,
            3.672119140625,
            -1.1996433734893799,
            -4.013830184936523,
            -3.899770736694336,
            -3.083857536315918,
            -1.9993606805801392,
            -3.7455379962921143,
            3.6634750366210938,
            -3.1895580291748047,
            -0.4526521563529968,
            -0.07258705794811249,
            1.92587411403656,
            0.9188727140426636,
            -3.4141321182250977,
            2.004871368408203,
            0.7795183658599854,
            2.371187686920166,
            -4.799032211303711,
            -2.5573554039001465,
            -3.667569160461426,
            -1.1098719835281372,
            2.729992628097534,
            1.7675023078918457,
            0.3762679696083069,
            1.8691043853759766,
            -1.4559816122055054,
            4.430106163024902,
            5.4620161056518555,
            1.9048235416412354,
            -0.7425835132598877,
            -4.0895280838012695,
            -0.08339399099349976,
            -1.484719157218933,
            0.8964569568634033,
            3.1592328548431396,
            -1.0887701511383057,
            6.7981109619140625,
            0.44989603757858276,
            3.1977782249450684,
            3.6121373176574707,
            0.7262827754020691,
            2.4206385612487793,
            -2.7492122650146484,
            0.06707624346017838,
            -0.696835994720459,
            0.9659966230392456,
            5.449060916900635,
            2.7009825706481934,
            -4.142443656921387,
            3.684579849243164,
            3.0521457195281982,
            3.0768823623657227,
            4.503795146942139,
            2.3031272888183594,
            1.0517572164535522,
            -0.05612385272979736,
            -2.3970541954040527,
            -1.4367915391921997,
            -1.7106499671936035,
            -1.5215460062026978,
            -1.5921775102615356,
            12.738295555114746,
            -5.120723247528076,
            -1.9126930236816406,
            -5.947516918182373,
            -2.744081974029541,
            0.03602859377861023,
            -2.8165173530578613,
            2.1537442207336426,
            -2.2248404026031494,
            -1.5657731294631958,
            -2.709942102432251,
            -4.697717666625977,
            2.8659675121307373,
            3.4081978797912598,
            0.4044796824455261,
            4.581008434295654,
            -2.1513819694519043,
            4.7063703536987305,
            -1.3333220481872559,
            3.801161766052246,
            -2.7276899814605713,
            3.535221576690674,
            0.6897968053817749,
            3.637753486633301,
            -5.537359237670898,
            3.400485038757324,
            0.729429304599762,
            -1.2559400796890259,
            -4.051274299621582,
            -6.621607303619385,
            -3.7765421867370605,
            -4.119960784912109,
            -0.43886715173721313,
            -2.8581159114837646,
            -2.5944619178771973,
            0.5247527360916138,
            6.931915283203125,
            0.7512084245681763,
            -2.7740960121154785,
            -4.1288652420043945,
            5.900196552276611,
            0.06159451603889465,
            -3.820382595062256,
            1.1396145820617676,
            -2.7255938053131104,
            -2.7391610145568848,
            -4.207555770874023,
            -4.245271682739258,
            1.3936429023742676,
            -0.8404765129089355,
            1.363533854484558,
            6.134547233581543,
            5.787693023681641,
            -0.4382510781288147,
            -0.09874510765075684,
            2.0599284172058105,
            4.419553756713867,
            0.9706686735153198,
            -0.0043299198150634766,
            3.094743013381958,
            3.4082870483398438,
            2.186697244644165,
            -2.6303529739379883,
            3.1531620025634766,
            -1.7614598274230957,
            2.9200191497802734,
            -1.8303158283233643,
            1.2906713485717773,
            -1.2160691022872925,
            0.8152024149894714,
            1.568076491355896,
            -0.41559529304504395,
            2.5338973999023438,
            -5.059806823730469,
            -1.5851516723632812,
            1.1349287033081055,
            -0.6348773837089539,
            4.765463352203369,
            0.4436514675617218,
            -1.0241432189941406,
            -1.0701751708984375,
            2.177700996398926,
            -0.5779109001159668,
            -2.9902520179748535,
            3.628728151321411,
            0.18796707689762115,
            -2.265486717224121,
            -1.992832064628601,
            3.1123547554016113,
            -2.066617012023926,
            -0.5287308096885681,
            -0.11348488926887512,
            0.8048608303070068,
            -1.5847384929656982,
            -4.942608833312988,
            2.412008285522461,
            -3.5742526054382324,
            2.265961170196533,
            -0.9366645812988281,
            1.541871428489685,
            -2.043405294418335,
            -2.0621933937072754,
            -3.538456439971924,
            -0.6196229457855225,
            1.4467819929122925,
            1.4048669338226318,
            -2.3525800704956055,
            -1.4589905738830566,
            2.8386077880859375,
            0.9264986515045166,
            3.5366897583007812,
            0.3454509973526001,
            -1.3702094554901123,
            -3.7307324409484863,
            -3.574908494949341,
            -2.379807472229004,
            3.53212833404541,
            -2.68026065826416,
            -0.5302826762199402,
            4.264291763305664,
            2.7491774559020996,
            4.289114952087402,
            4.53635311126709,
            2.325914144515991,
            -0.7973223924636841,
            2.9127280712127686,
            3.550480365753174,
            -1.042292594909668,
            0.806145429611206,
            -0.827600359916687,
            -6.445382118225098,
            3.156855821609497,
            -1.4954837560653687,
            -1.0120172500610352,
            -1.1590744256973267,
            -4.745319366455078,
            -0.2628329396247864,
            -2.282505750656128,
            -4.606207847595215,
            4.568957328796387,
            1.1478805541992188,
            1.4959721565246582,
            -2.953706741333008,
            -0.811371922492981,
            -3.7623612880706787,
            -0.45834046602249146,
            -4.660202980041504,
            3.044597625732422,
            0.11999315023422241,
            -1.0526394844055176,
            2.8995983600616455,
            0.27080780267715454,
            -0.9397596120834351,
            1.5375198125839233,
            -3.853577136993408,
            -3.5900895595550537,
            1.0673983097076416,
            1.1578631401062012,
            0.11671453714370728,
            2.1304750442504883,
            -2.5467138290405273,
            3.5245871543884277,
            0.31874704360961914,
            4.0016069412231445,
            4.599257469177246,
            5.007253170013428,
            2.34161114692688,
            -4.087499618530273,
            -1.666966438293457,
            -4.512495040893555,
            1.7990375757217407,
            3.638326644897461,
            -3.467026472091675,
            1.4894273281097412,
            1.9722532033920288,
            1.4439197778701782,
            -2.8653693199157715,
            0.9129148125648499,
            -2.786832571029663,
            4.533672332763672,
            -2.2382407188415527,
            -2.7508063316345215,
            -0.4341747462749481,
            -0.4330442547798157,
            -0.19791902601718903,
            -4.435041904449463,
            1.553714632987976,
            -3.484999656677246,
            -0.6329450607299805,
            -1.4401226043701172,
            -0.8256579637527466,
            -2.4163143634796143,
            1.3471570014953613,
            2.6024439334869385,
            1.929084300994873,
            -0.7751691341400146,
            -1.5835061073303223,
            4.475043296813965,
            -2.3705220222473145,
            -1.7079145908355713,
            -0.023854821920394897,
            5.312001705169678,
            2.153433322906494,
            -3.352412223815918,
            2.0083534717559814,
            -1.8058148622512817,
            1.9316365718841553,
            -0.16879844665527344,
            1.6167285442352295,
            5.506505966186523,
            3.3083300590515137,
            0.6695196032524109,
            -2.9670000076293945,
            2.073425769805908,
            -1.0029703378677368,
            -3.453087091445923,
            -0.7924042344093323,
            -4.449771881103516,
            2.6324806213378906,
            -4.330428123474121,
            -4.9506025314331055,
            1.1380077600479126,
            -4.511590480804443,
            2.3856148719787598,
            -0.9408309459686279,
            -0.006973564624786377,
            -0.23467856645584106,
            -1.8961693048477173,
            -1.5628377199172974,
            -2.695647716522217,
            0.1702495515346527,
            -0.9785945415496826,
            0.5202052593231201,
            1.1054279804229736,
            1.779881238937378,
            4.938354969024658,
            6.583106994628906,
            0.9130258560180664,
            -0.5814478397369385,
            -0.8822510242462158,
            -0.6788033843040466,
            1.0432043075561523,
            1.2863590717315674,
            0.5724259614944458,
            -3.265566825866699,
            2.503882884979248,
            17.438316345214844,
            -1.7913947105407715,
            2.100947856903076,
            -3.726067543029785,
            1.7812530994415283,
            -3.9300107955932617,
            -1.7433006763458252,
            0.11145982146263123,
            3.0870161056518555,
            2.498363494873047,
            1.8301067352294922,
            -5.182787895202637,
            -0.9835495948791504,
            1.4075347185134888,
            1.9731547832489014,
            1.7156987190246582,
            -1.7280564308166504,
            -1.2625923156738281,
            0.3080229163169861,
            -1.156032919883728,
            1.6023855209350586,
            -2.5541937351226807,
            -2.4297220706939697,
            -0.350238561630249,
            0.42680370807647705,
            1.8064168691635132,
            -2.1942501068115234,
            0.380013108253479,
            -4.792719841003418,
            -1.9085373878479004,
            5.071965217590332,
            -0.6429282426834106,
            4.852699279785156,
            2.289869546890259,
            -0.25783571600914,
            0.31530478596687317,
            6.448027610778809,
            0.013842374086380005,
            4.972917556762695,
            1.4284887313842773,
            -0.3453957438468933,
            1.519162893295288,
            -3.783670425415039,
            3.5317935943603516,
            -0.9421876072883606,
            -0.988044023513794,
            1.2419407367706299,
            -2.0971121788024902,
            -0.16399940848350525,
            5.0186448097229,
            -0.32506436109542847,
            1.3157458305358887,
            -1.3978803157806396,
            0.24579918384552002,
            1.8888331651687622,
            3.759190082550049,
            -1.4962482452392578,
            -1.8924353122711182,
            2.987076997756958,
            -1.2603894472122192,
            -0.8289183378219604,
            0.07058337330818176,
            -0.09186667203903198,
            -2.912126302719116,
            0.06283795833587646,
            1.410591959953308,
            -3.2211427688598633,
            -0.23038485646247864,
            5.902328014373779,
            3.1881515979766846,
            3.9783222675323486,
            2.4066483974456787,
            -0.034516334533691406,
            -3.939481019973755,
            -1.7053285837173462,
            -5.171022415161133,
            2.2172598838806152,
            -0.9275931119918823,
            2.7613778114318848,
            5.39756441116333,
            -2.0973660945892334,
            3.0451536178588867,
            -3.8249950408935547,
            1.288170576095581,
            4.744022369384766,
            -3.7020349502563477,
            3.976853609085083,
            -2.208949565887451,
            -2.0117223262786865,
            1.6455823183059692,
            -0.4017658233642578,
            -2.8299455642700195,
            1.5268547534942627,
            0.5273249745368958,
            3.567328453063965,
            -3.5303456783294678,
            -2.494947671890259,
            -0.2961602509021759,
            -2.8319060802459717,
            -4.8763556480407715,
            5.410187721252441,
            2.952918767929077,
            2.4218101501464844,
            -5.547008037567139,
            1.7673381567001343,
            1.2986531257629395,
            -1.1224316358566284,
            -4.484440326690674,
            -5.39432430267334,
            -0.9775139689445496,
            6.66854190826416,
            -2.523744583129883,
            -2.550408124923706,
            1.9596936702728271,
            -1.2304973602294922,
            2.844290256500244,
            -1.3620078563690186,
            3.197923183441162,
            1.7872060537338257,
            2.5055525302886963,
            -1.450781226158142,
            -2.29358172416687,
            -0.9183802604675293,
            -5.19581937789917,
            0.5151280164718628,
            0.5623996257781982,
            0.4103521406650543,
            -0.6665691137313843,
            0.9996809959411621,
            -1.333446741104126,
            -1.9866502285003662,
            -2.007249116897583,
            0.12083861231803894,
            -0.0989057719707489,
            1.0248382091522217,
            1.321947455406189,
            0.28976550698280334,
            1.2048943042755127,
            -3.5958917140960693,
            2.7368075847625732,
            1.6368000507354736,
            -2.3249564170837402,
            -1.553349256515503,
            8.650861740112305,
            -3.4842019081115723,
            1.2596769332885742,
            -3.079418659210205,
            0.13945026695728302,
            -1.2243943214416504,
            0.419741153717041,
            0.92760169506073,
            0.5331105589866638,
            3.991889715194702,
            -1.0522780418395996,
            -0.5841057896614075,
            -1.2875158786773682
        ]
    },
    "authors": [
        {
            "authorId": "2284680449",
            "name": "Pirzada Suhail"
        },
        {
            "authorId": "2284680965",
            "name": "Amit Sethi"
        }
    ],
    "references": [
        {
            "paperId": "3e33d544dd210f8221bc50019ec219d652550210",
            "title": "Network Inversion of Binarised Neural Nets"
        },
        {
            "paperId": "adf3b591281688b7e71b254ab931b2aa39b4b59f",
            "title": "Empirical Evaluation of Rectified Activations in Convolutional Network"
        },
        {
            "paperId": "995c5f5e62614fcb4d2796ad2faab969da51713e",
            "title": "Batch Normalization: Accelerating Deep Network Training by Reducing Internal Covariate Shift"
        },
        {
            "paperId": "46f74231b9afeb0c290d6d550043c55045284e5f",
            "title": "The MNIST Database of Handwritten Digit Images for Machine Learning Research [Best of the Web]"
        },
        {
            "paperId": "04a882743eadac813f11c6c78f1b7b8434574b13",
            "title": "Inversion of feedforward neural networks: algorithms and applications"
        },
        {
            "paperId": "4862bd12c53f160862e0bca5f758788829764954",
            "title": "Inversion of neural networks by gradient descent"
        },
        {
            "paperId": "34f25a8704614163c4095b3ee2fc969b60de4698",
            "title": "Dropout: a simple way to prevent neural networks from overfitting"
        }
    ]
}